json_get-1.1.0.dist-info/LICENSE.txt
json_get-1.1.0.dist-info/METADATA
json_get-1.1.0.dist-info/RECORD
json_get-1.1.0.dist-info/WHEEL
json_get-1.1.0.dist-info/top_level.txt
jsonget/__init__.py
jsonget/py.typed
jsonget_test/__init__.py
