Metadata-Version: 2.1
Name: json-get
Version: 1.1.0
Summary: Get values from JSON objects using a path expression
Home-page: https://github.com/srittau/python-json-get
Author: Sebastian Rittau
Author-email: srittau@rittau.biz
License: MIT
Platform: UNKNOWN
Classifier: Development Status :: 5 - Production/Stable
Classifier: Intended Audience :: Developers
Classifier: License :: OSI Approved :: MIT License
Classifier: Programming Language :: Python :: 3
Classifier: Programming Language :: Python :: 3.5
Classifier: Programming Language :: Python :: 3.6
Classifier: Topic :: Software Development
Requires-Python: >=3.5
